Workbook

Sheet Bookings
A1: Check-in date | B1: Check-out date | C1: Guest Name | D1: Country | E1: Adults | F1: Children | G1: Total guests | H1: Sofa Bed | I1: Baby Crib | J1: Parking | K1: Platform | L1: Nights | M1: Revenue for stay (€) | N1: Transportation Cost (€) | O1: Laundry Cost (€) | P1: Consumable Cost (€) | Q1: Bank Fees (€) | R1: Per-stay expenses (€) | S1: Net Income Before Fixed Costs (€) | T1: Check-in Month | U1: Check-in Year | V1: Notes
A2: 45787 | B2: 45791 | C2: Magnus Lange | D2: Denmark | E2: 2 | F2: 0 | G2: 2 | H2: No | I2: No | J2: No | K2: Airbnb | L2: 4 | M2: 170.72 | N2: 5 | O2: 5 | P2: 4 | Q2: 6 | R2: 20 | S2: 150.72 | T2: 5 | U2: 2025
A3: 45803 | B3: 45817 | C3: Karmen Cilakova | D3: USA | E3: 1 | F3: 0 | G3: 1 | H3: No | I3: No | J3: Yes | K3: Airbnb | L3: 14 | M3: 574.24 | N3: 5 | O3: 5 | P3: 4 | Q3: 6 | R3: 20 | S3: 554.24 | T3: 5 | U3: 2025
A4: 45820 | B4: 45830 | C4: Alexander Becker | D4: Germany | E4: 2 | F4: 0 | G4: 2 | H4: Yes | I4: No | J4: No | K4: Airbnb | L4: 10 | M4: 499.55 | N4: 5 | O4: 5 | P4: 4 | Q4: 0 | R4: 14 | S4: 485.55 | T4: 6 | U4: 2025
A5: 45847 | B5: 45853 | C5: Family Plavsa Plavsa | D5: Monte Negro | E5: 1 | F5: 0 | G5: 1 | H5: No | I5: No | J5: No | K5: Airbnb | L5: 6 | M5: 200.79 | N5: 5 | O5: 5 | P5: 4 | Q5: 0 | R5: 14 | S5: 186.79 | T5: 7 | U5: 2025
A6: 45854 | B6: 45857 | C6: Ali Erdeyer | D6: Turkey | E6: 3 | F6: 0 | G6: 3 | H6: Yes | I6: No | J6: Yes | K6: Airbnb | L6: 3 | M6: 90.36 | N6: 5 | O6: 5 | P6: 4 | Q6: 0 | R6: 14 | S6: 76.36 | T6: 7 | U6: 2025
A7: 45857 | B7: 45865 | C7: Patsy Vanfleteren | D7: Belgium | E7: 3 | F7: 0 | G7: 3 | H7: Yes | I7: No | J7: Yes | K7: Booking | L7: 8 | M7: 289.19 | N7: 5 | O7: 5 | P7: 4 | Q7: 0 | R7: 14 | S7: 275.19 | T7: 7 | U7: 2025
A8: 45868 | B8: 45883 | C8: Daniela Dahlenburg | D8: Germany | E8: 2 | F8: 1 | G8: 3 | H8: Yes | I8: No | J8: Yes | K8: Booking | L8: 15 | M8: 629.71 | N8: 5 | O8: 5 | P8: 4 | Q8: 0 | R8: 14 | S8: 615.71 | T8: 7 | U8: 2025
A9: 45883 | B9: 45887 | C9: Megi Milošević Mihajlovski | D9: Slovenia | E9: 2 | F9: 2 | G9: 4 | H9: Yes | I9: Yes | J9: Yes | K9: Booking | L9: 4 | M9: 200.24 | N9: 5 | O9: 5 | P9: 4 | Q9: 0 | R9: 14 | S9: 186.24 | T9: 8 | U9: 2025
A10: 45887 | B10: 45890 | C10: Emre Tuncay | D10: Turkey | E10: 2 | F10: 0 | G10: 2 | H10: No | I10: No | J10: No | K10: Airbnb | L10: 3 | M10: 112.21 | N10: 5 | O10: 5 | P10: 4 | Q10: 0 | R10: 14 | S10: 98.21 | T10: 8 | U10: 2025
A11: 45895 | B11: 45899 | C11: Nadia Dridi | D11: France | E11: 2 | F11: 0 | G11: 2 | H11: No | I11: No | J11: Yes | K11: Airbnb | L11: 4 | M11: 169.31 | N11: 5 | O11: 5 | P11: 4 | Q11: 6 | R11: 20 | S11: 149.31 | T11: 8 | U11: 2025
A12: 45904 | B12: 45911 | C12: Milo Drost | D12: Netherlands | E12: 1 | F12: 0 | G12: 1 | H12: No | I12: No | J12: No | K12: Airbnb | L12: 7 | M12: 271.94 | N12: 5 | O12: 5 | P12: 4 | Q12: 6 | R12: 20 | S12: 251.94 | T12: 9 | U12: 2025
A13: 45935 | B13: 45938 | C13: Su Beril Sider | D13: Turkey | E13: 2 | F13: 0 | G13: 2 | H13: No | I13: No | J13: No | K13: Airbnb | L13: 3 | M13: 145.5 | N13: 5 | O13: 5 | P13: 4 | Q13: 6 | R13: 20 | S13: 125.5 | T13: 10 | U13: 2025
... A26: 46095 | B26: 46098 | C26: Enikő Tóth | D26: Netherlands | E26: 2 | F26: 0 | G26: 2 | H26: No | I26: No | J26: No | K26: Booking | L26: 3 | M26: 123.24 | N26: 5 | O26: 5 | P26: 3.77 | Q26: 6 | R26: 19.77 | S26: 103.47 | T26: 3 | U26: 2026

Sheet Monthly_Costs
A1: Year | B1: MONTH | C1: Electricity (den) | D1: Electricity (€) | E1: Water (den) | F1: Water (€) | G1: Property Management Fee (den) | H1: Property Management Fee (€) | I1: Internet (€) | J1: TV (€) | K1: Other fixed costs (€) | L1: Total Fixed Costs (€)
A2: 2025 | B2: 1 | C2: 0 | D2: 0 | E2: 0 | F2: 0 | G2: 0 | H2: 0 | I2: 0 | J2: 0 | K2: 0 | L2: 0
A3: 2025 | B3: 2 | C3: 0 | D3: 0 | E3: 0 | F3: 0 | G3: 0 | H3: 0 | I3: 0 | J3: 0 | K3: 0 | L3: 0
A4: 2025 | B4: 3 | C4: 674 | D4: 10.957568 | E4: 291 | F4: 4.7309381 | G4: 2504 | H4: 40.708828 | I4: 0 | J4: 3.24 | K4: 0 | L4: 59.637334
A5: 2025 | B5: 4 | C5: 1025 | D5: 16.663957 | E5: 419 | F5: 6.8119005 | G5: 2696 | H5: 43.830272 | I5: 0 | J5: 3.24 | K5: 0 | L5: 70.546129
A6: 2025 | B6: 5 | C6: 1312 | D6: 21.329865 | E6: 651 | F6: 10.583645 | G6: 2692 | H6: 43.765241 | I6: 0 | J6: 3.24 | K6: 0 | L6: 78.918751
A7: 2025 | B7: 6 | C7: 2050 | D7: 33.327914 | E7: 411 | F7: 6.6818404 | G7: 2787 | H7: 45.309706 | I7: 0 | J7: 3.24 | K7: 0 | L7: 88.55946
A8: 2025 | B8: 7 | C8: 3284 | D8: 53.389693 | E8: 211 | F8: 3.4303365 | G8: 2755 | H8: 44.789465 | I8: 0 | J8: 3.24 | K8: 0 | L8: 104.84949
A9: 2025 | B9: 8 | C9: 2823 | D9: 45.894976 | E9: 611 | F9: 9.9333442 | G9: 2816 | H9: 45.781174 | I9: 0 | J9: 3.24 | K9: 0 | L9: 104.84949
A10: 2025 | B10: 9 | C10: 2304 | D10: 37.457324 | E10: 431 | F10: 7.0069907 | G10: 2701 | H10: 43.911559 | I10: 0 | J10: 3.24 | K10: 0 | L10: 91.615874
A11: 2025 | B11: 10 | C11: 2838 | D11: 46.138839 | E11: 211 | F11: 3.4303365 | G11: 2927 | H11: 47.585758 | I11: 11 | J11: 3.24 | K11: 0 | L11: 111.39493
A12: 2025 | B12: 11 | C12: 0 | D12: 0 | E12: 475 | F12: 7.7223216 | G12: 0 | H12: 0 | I12: 11 | J12: 3.24 | K12: 0 | L12: 21.962322
A13: 2025 | B13: 12 | C13: 0 | D13: 0 | E13: 0 | F13: 0 | G13: 0 | H13: 0 | I13: 0 | J13: 0 | K13: 0 | L13: 0
C14: 0 | D14: 0 | E14: 0 | F14: 0 | G14: 0 | H14: 0 | I14: 0 | J14: 0 | K14: 0 | L14: 0
A15: 2026 | B15: 1 | C15: 0 | D15: 0 | E15: 0 | F15: 0 | G15: 0 | H15: 0 | I15: 0 | J15: 0 | K15: 0 | L15: 0
A16: 2026 | B16: 2 | C16: 0 | D16: 0 | E16: 0 | F16: 0 | G16: 0 | H16: 0 | I16: 0 | J16: 0 | K16: 0 | L16: 0
A17: 2026 | B17: 3 | C17: 0 | D17: 0 | E17: 0 | F17: 0 | G17: 0 | H17: 0 | I17: 0 | J17: 0 | K17: 0 | L17: 0
A18: 2026 | B18: 4 | C18: 0 | D18: 0 | E18: 0 | F18: 0 | G18: 0 | H18: 0 | I18: 0 | J18: 0 | K18: 0 | L18: 0
A19: 2026 | B19: 5 | C19: 0 | D19: 0 | E19: 0 | F19: 0 | G19: 0 | H19: 0 | I19: 0 | J19: 0 | K19: 0 | L19: 0
A20: 2026 | B20: 6 | C20: 0 | D20: 0 | E20: 0 | F20: 0 | G20: 0 | H20: 0 | I20: 0 | J20: 0 | K20: 0 | L20: 0
A21: 2026 | B21: 7 | C21: 0 | D21: 0 | E21: 0 | F21: 0 | G21: 0 | H21: 0 | I21: 0 | J21: 0 | K21: 0 | L21: 0
A22: 2026 | B22: 8 | C22: 0 | D22: 0 | E22: 0 | F22: 0 | G22: 0 | H22: 0 | I22: 0 | J22: 0 | K22: 0 | L22: 0
A23: 2026 | B23: 9 | C23: 0 | D23: 0 | E23: 0 | F23: 0 | G23: 0 | H23: 0 | I23: 0 | J23: 0 | K23: 0 | L23: 0
A24: 2026 | B24: 10 | C24: 0 | D24: 0 | E24: 0 | F24: 0 | G24: 0 | H24: 0 | I24: 0 | J24: 0 | K24: 0 | L24: 0
A25: 2026 | B25: 11 | C25: 0 | D25: 0 | E25: 0 | F25: 0 | G25: 0 | H25: 0 | I25: 0 | J25: 0 | K25: 0 | L25: 0
A26: 2026 | B26: 12 | C26: 0 | D26: 0 | E26: 0 | F26: 0 | G26: 0 | H26: 0 | I26: 0 | J26: 0 | K26: 0 | L26: 0

Sheet Toiletries
A1: Item | B1: Unit Price (MKD) | C1: Units per Stay | D1: Total (MKD)
A2: Tootbrush | B2: 6 | C2: 1 | D2: 6
A3: Tootpaste | B3: 5 | C3: 1 | D3: 5
A4: Soap | B4: 15 | C4: 1 | D4: 15
A5: Disposable Slippers | B5: 5 | C5: 1 | D5: 5
A6: Cotton Pads | B6: 1 | C6: 2 | D6: 2
A7: Cotton Swabs | B7: 1 | C7: 2 | D7: 2
A8: Floss Picks | B8: 1 | C8: 2 | D8: 2
A9: Toilet Paper | B9: 15 | C9: 3 | D9: 45
A10: Botle of Water | B10: 20 | C10: 1 | D10: 20
A11: Coffee capsules | B11: 20 | C11: 6 | D11: 120
A12: Tea | B12: 5 | C12: 2 | D12: 10
B13: 0 | C13: 0 | D13: 0
B14: 0 | C14: 0 | D14: 0

Sheet Summary
A1: OVERALL SUMMARY | D1: Month (1-12) | E1: Revenue (€) | F1: Nights | G1: Net income before fixed (€) | H1: Average price per night (€)
A2: Reservations count | B2: =COUNT(Bookings!L:L) | D2: 1 | E2: =SUMIFS(Bookings!$M:$M,Bookings!$U:$U,$B$15,Bookings!$T:$T,$D2) | F2: =SUMIFS(Bookings!$L:$L,Bookings!$U:$U,$B$15,Bookings!$T:$T,$D2) | G2: =SUMIFS(Bookings!$S:$S,Bookings!$U:$U,$B$15,Bookings!$T:$T,$D2) | H2: =IF(F2>0,E2/F2,"")
A3: Total nights | B3: =SUM(Bookings!L:L) | D3: 2 | E3: =SUMIFS(Bookings!$M:$M,Bookings!$U:$U,$B$15,Bookings!$T:$T,$D3) | F3: =SUMIFS(Bookings!$L:$L,Bookings!$U:$U,$B$15,Bookings!$T:$T,$D3) | G3: =SUMIFS(Bookings!$S:$S,Bookings!$U:$U,$B$15,Bookings!$T:$T,$D3) | H3: =IF(F3>0,E3/F3,"")
A4: Total revenue (€) | B4: =SUM(Bookings!M:M) | D4: 3 | E4: =SUMIFS(Bookings!$M:$M,Bookings!$U:$U,$B$15,Bookings!$T:$T,$D4) | F4: =SUMIFS(Bookings!$L:$L,Bookings!$U:$U,$B$15,Bookings!$T:$T,$D4) | G4: =SUMIFS(Bookings!$S:$S,Bookings!$U:$U,$B$15,Bookings!$T:$T,$D4) | H4: =IF(F4>0,E4/F4,"")
A5: Total Per-stay expenses (€) | B5: =SUM(Bookings!R:R) | D5: 4 | E5: =SUMIFS(Bookings!$M:$M,Bookings!$U:$U,$B$15,Bookings!$T:$T,$D5) | F5: =SUMIFS(Bookings!$L:$L,Bookings!$U:$U,$B$15,Bookings!$T:$T,$D5) | G5: =SUMIFS(Bookings!$S:$S,Bookings!$U:$U,$B$15,Bookings!$T:$T,$D5) | H5: =IF(F5>0,E5/F5,"")
A6: Total monthly costs (€) | B6: =Monthly_Costs!L14 | D6: 5 | E6: =SUMIFS(Bookings!$M:$M,Bookings!$U:$U,$B$15,Bookings!$T:$T,$D6) | F6: =SUMIFS(Bookings!$L:$L,Bookings!$U:$U,$B$15,Bookings!$T:$T,$D6) | G6: =SUMIFS(Bookings!$S:$S,Bookings!$U:$U,$B$15,Bookings!$T:$T,$D6) | H6: =IF(F6>0,E6/F6,"")
A7: Net income after ALL costs (€) | B7: =B4-B5-B6 | D7: 6 | E7: =SUMIFS(Bookings!$M:$M,Bookings!$U:$U,$B$15,Bookings!$T:$T,$D7) | F7: =SUMIFS(Bookings!$L:$L,Bookings!$U:$U,$B$15,Bookings!$T:$T,$D7) | G7: =SUMIFS(Bookings!$S:$S,Bookings!$U:$U,$B$15,Bookings!$T:$T,$D7) | H7: =IF(F7>0,E7/F7,"")
D8: 7 | E8: =SUMIFS(Bookings!$M:$M,Bookings!$U:$U,$B$15,Bookings!$T:$T,$D8) | F8: =SUMIFS(Bookings!$L:$L,Bookings!$U:$U,$B$15,Bookings!$T:$T,$D8) | G8: =SUMIFS(Bookings!$S:$S,Bookings!$U:$U,$B$15,Bookings!$T:$T,$D8) | H8: =IF(F8>0,E8/F8,"")
A9: Average price per night (€) | B9: =IF(B3>0,B4/B3,"") | D9: 8 | E9: =SUMIFS(Bookings!$M:$M,Bookings!$U:$U,$B$15,Bookings!$T:$T,$D9) | F9: =SUMIFS(Bookings!$L:$L,Bookings!$U:$U,$B$15,Bookings!$T:$T,$D9) | G9: =SUMIFS(Bookings!$S:$S,Bookings!$U:$U,$B$15,Bookings!$T:$T,$D9) | H9: =IF(F9>0,E9/F9,"")
A10: Total rented nights | B10: =B3 | D10: 9 | E10: =SUMIFS(Bookings!$M:$M,Bookings!$U:$U,$B$15,Bookings!$T:$T,$D10) | F10: =SUMIFS(Bookings!$L:$L,Bookings!$U:$U,$B$15,Bookings!$T:$T,$D10) | G10: =SUMIFS(Bookings!$S:$S,Bookings!$U:$U,$B$15,Bookings!$T:$T,$D10) | H10: =IF(F10>0,E10/F10,"")
A11: Approx. months rented (nights / 30) | B11: =IF(B3>0,B3/30,"") | D11: 10 | E11: =SUMIFS(Bookings!$M:$M,Bookings!$U:$U,$B$15,Bookings!$T:$T,$D11) | F11: =SUMIFS(Bookings!$L:$L,Bookings!$U:$U,$B$15,Bookings!$T:$T,$D11) | G11: =SUMIFS(Bookings!$S:$S,Bookings!$U:$U,$B$15,Bookings!$T:$T,$D11) | H11: =IF(F11>0,E11/F11,"")
A12: Average revenue per month (€) | B12: =IF(B11>0,B4/B11,"") | D12: 11 | E12: =SUMIFS(Bookings!$M:$M,Bookings!$U:$U,$B$15,Bookings!$T:$T,$D12) | F12: =SUMIFS(Bookings!$L:$L,Bookings!$U:$U,$B$15,Bookings!$T:$T,$D12) | G12: =SUMIFS(Bookings!$S:$S,Bookings!$U:$U,$B$15,Bookings!$T:$T,$D12) | H12: =IF(F12>0,E12/F12,"")
D13: 12 | E13: =SUMIFS(Bookings!$M:$M,Bookings!$U:$U,$B$15,Bookings!$T:$T,$D13) | F13: =SUMIFS(Bookings!$L:$L,Bookings!$U:$U,$B$15,Bookings!$T:$T,$D13) | G13: =SUMIFS(Bookings!$S:$S,Bookings!$U:$U,$B$15,Bookings!$T:$T,$D13) | H13: =IF(F13>0,E13/F13,"")
A15: Year for monthly overview: | B15: 2025
E17: Reservations count | F17: Total Nights | G17: Total revenue (€) | H17: Total variable costs (€) | I17: Net income without Fixed costs | J17: Average price per night (€) | K17: Approx. months rented (nights / 30) | L17: Average revenue per month (€)
D18: Airbnb | E18: =COUNTIF(Bookings!$K:$K,"Airbnb") | F18: =SUMIFS(Bookings!L:L, Bookings!K:K, "Airbnb") | G18: =SUMIFS(Bookings!M:M, Bookings!K:K, "Airbnb") | H18: =SUMIFS(Bookings!R:R, Bookings!K:K, "Airbnb") | I18: =SUM(G18-H18) | J18: =IF(F18>0,G18/F18,"") | K18: =IF(F18>0,F18/30,"") | L18: =IF(K18>0,G18/K18,"")
A19: Average stay | B19: =SUM(B3/B2) | D19: Booking | E19: =COUNTIF(Bookings!$K:$K,"Booking") | F19: =SUMIFS(Bookings!L:L, Bookings!K:K, "Booking") | G19: =SUMIFS(Bookings!M:M, Bookings!K:K, "Booking") | H19: =SUMIFS(Bookings!R:R, Bookings!K:K, "Booking") | I19: =SUM(G19-H19) | J19: =IF(F19>0,G19/F19,"") | K19: =IF(F19>0,F19/30,"") | L19: =IF(K19>0,G19/K19,"")
D22: Sofa Bed used | E22: =COUNTIF(Bookings!H:H,"Yes")
D23: Baby Crib used | E23: =COUNTIF(Bookings!I:I,"Yes")
D24: Parking used | E24: =COUNTIF(Bookings!J:J,"Yes")
